{
    "First Name": "Scott", 
    "Email": "scott.earnest@enron.com", 
    "additional": {
        "Last Name": "Earnest", 
        "Mobile": [], 
        "Phone": []
    }
}{
    "First Name": "Sally", 
    "Email": "sally.beck@enron.com", 
    "additional": {
        "Last Name": "Beck"
    }
}{
    "First Name": "Ted", 
    "Email": "ted.murphy@enron.com", 
    "additional": {
        "Last Name": "Murphy"
    }
}{
    "First Name": "Vince", 
    "Email": "vince.kaminski@enron.com", 
    "additional": {
        "Last Name": "Kaminski"
    }
}{
    "First Name": "Tani", 
    "Email": "tani.nath@enron.com", 
    "additional": {
        "Last Name": "Nath"
    }
}{
    "First Name": "Dale", 
    "Email": "dale.surbey@enron.com", 
    "additional": {
        "Last Name": "Surbey"
    }
}{
    "First Name": "Eric", 
    "Email": "eric.groves@enron.com", 
    "additional": {
        "Last Name": "Groves"
    }
}{
    "First Name": "Bjorn", 
    "Email": "bjorn.hagelmann@enron.com", 
    "additional": {
        "Last Name": "Hagelmann"
    }
}{
    "First Name": "Connie", 
    "Email": "connie.sutton@enron.com", 
    "additional": {
        "Last Name": "Sutton", 
        "Mobile": [], 
        "Phone": []
    }
}{
    "First Name": "Mary", 
    "Email": "mary.solmonson@enron.com", 
    "additional": {
        "Last Name": "Solmonson"
    }
}{
    "First Name": "Brent", 
    "Email": "brent.price@enron.com", 
    "additional": {
        "Last Name": "Price", 
        "Mobile": [], 
        "Phone": []
    }
}{
    "First Name": "Anshuman", 
    "Email": "anshuman.srivastav@enron.com", 
    "additional": {
        "Last Name": "Srivastav", 
        "Mobile": [], 
        "Phone": []
    }
}